sort_prices/__init__.py
sort_prices/sorter.py
sort_prices-1.0.0.dist-info/METADATA
sort_prices-1.0.0.dist-info/WHEEL
sort_prices-1.0.0.dist-info/top_level.txt
sort_prices-1.0.0.dist-info/RECORD
